AUTHORS
INSTALL
LICENSE
MANIFEST.in
README.md
setup.py
cherrypy_wsgiserver.egg-info/PKG-INFO
cherrypy_wsgiserver.egg-info/SOURCES.txt
cherrypy_wsgiserver.egg-info/dependency_links.txt
cherrypy_wsgiserver.egg-info/top_level.txt
wsgiserver/__init__.py
wsgiserver/ssl_builtin.py
wsgiserver/ssl_pyopenssl.py