Metadata-Version: 1.0
Name: cherrypy-wsgiserver
Version: 0.1dev
Summary: Wsgiserver configured for cherrypy and django
Home-page: https://github.com/od-eon/cherrypy-wsgiserver
Author: Calvin Cheng
Author-email: calvin@calvinx.com
License: LICENSE
Platform: UNKNOWN
